swmconsole/run.py
swmconsole-0.1.4.dist-info/LICENSE
swmconsole-0.1.4.dist-info/METADATA
swmconsole-0.1.4.dist-info/WHEEL
swmconsole-0.1.4.dist-info/entry_points.txt
swmconsole-0.1.4.dist-info/top_level.txt
swmconsole-0.1.4.dist-info/RECORD
