Metadata-Version: 2.1
Name: swmconsole
Version: 0.1.4
Summary: Console terminal for swm-core
Author-email: Taras Shapovalov <taras@iclouds.net>
License: BSD 3-Clause License
Project-URL: Homepage, https://openworkload.org
Project-URL: Documentation, https://openworkload.org
Project-URL: Repository, https://github.com/openworkload/swm-console-term
Project-URL: Tests, https://github.com/openworkload/swm-console-term/tree/master/test
Project-URL: Issues, https://github.com/openworkload/swm-console-term/issues
Project-URL: Distribution, https://pypi.org/project/swmconsole
Keywords: hpc,high performance computing,cloud,cloud computing,open workload,sky port
Classifier: Environment :: Console
Classifier: Development Status :: 3 - Alpha
Classifier: Programming Language :: Python :: 3
Classifier: License :: OSI Approved :: BSD License
Classifier: Operating System :: OS Independent
Classifier: Programming Language :: Python :: 3.10
Classifier: Programming Language :: Python :: 3 :: Only
Requires-Python: ~=3.10
License-File: LICENSE
Requires-Dist: swmclient>=0.1.7
Requires-Dist: tabulate
Requires-Dist: attrs
Provides-Extra: build
Requires-Dist: build==1.2.1; extra == "build"
Provides-Extra: publish
Requires-Dist: twine==5.1.1; extra == "publish"
Provides-Extra: test
Requires-Dist: pytest; extra == "test"
